HISTORY.rst
MANIFEST.in
README.rst
setup.py
bts_proxy/__init__.py
bts_proxy/proxy.py
bts_proxy.egg-info/PKG-INFO
bts_proxy.egg-info/SOURCES.txt
bts_proxy.egg-info/dependency_links.txt
bts_proxy.egg-info/entry_points.txt
bts_proxy.egg-info/requires.txt
bts_proxy.egg-info/top_level.txt