Metadata-Version: 1.1
Name: bts-proxy
Version: 0.1
Summary: BitShares RPC proxy
Home-page: https://github.com/wackou/bts_proxy
Author: Nicolas Wack
Author-email: wackou@gmail.com
License: UNKNOWN
Keywords: BitShares RPC proxy
Platform: UNKNOWN
Classifier: Development Status :: 3 - Alpha
Classifier: License :: OSI Approved :: GNU General Public License v3 or later (GPLv3+)
Classifier: Operating System :: OS Independent
Classifier: Programming Language :: Python :: 3
Classifier: Programming Language :: Python :: 3.3
Classifier: Programming Language :: Python :: 3.4
